{
  "canisters": {
    "wayfare_backend": {
      "main": "src/wayfare_backend/main.mo",
      "type": "motoko"
    },
    "ticket": {
      "main": "src/wayfare_backend/ticket.mo",
      "type": "motoko"
    },
    "wayfare_frontend": {
      "dependencies": [
        "wayfare_backend",
        "ticket"
      ],
      "source": [
        "src/wayfare_frontend/dist"
      ],
      "type": "assets",
      "workspace": "wayfare_frontend"
    }
  },
  "defaults": {
    "build": {
      "args": "",
      "packtool": "mops sources"
    }
  },
  "output_env_file": ".env",
  "version": 1
}